{
    "m_Version": 12,
    "DisplayName": "Forward Operator Gear Bags",
    "Icon": "Backpack",
    "Color": "FF0000FF",
    "IsExchange": 0,
    "InitStockPercent": 0.0,
    "Items": [
        {
            "ClassName": "FOG_Bag_6ShBagT",
            "MaxPriceThreshold": 9500,
            "MinPriceThreshold": 9500,
            "SellPricePercent": 30.0,
            "MaxStockThreshold": 1,
            "MinStockThreshold": 1,
            "QuantityPercent": 0,
            "SpawnAttachments": [],
            "Variants": [
				"FOG_Bag_6ShBagT_Green",
				"FOG_Bag_6ShBagT_BlackEMR",
				"FOG_Bag_6ShBagT_Black",
				"FOG_Bag_6ShBagT_RG",
				"FOG_Bag_6ShBagT_CB"

            ]
        },
		{
            "ClassName": "FOG_Bergen_Rucksack",
            "MaxPriceThreshold": 6500,
            "MinPriceThreshold": 6500,
            "SellPricePercent": 30.0,
            "MaxStockThreshold": 1,
            "MinStockThreshold": 1,
            "QuantityPercent": 0,
            "SpawnAttachments": [],
            "Variants": [
				"FOG_Bergen_Rucksack_Black",
				"FOG_Bergen_Rucksack_Green",
				"FOG_Bergen_Rucksack_Woodland",
				"FOG_Bergen_Rucksack_Multicam",
				"FOG_Bergen_Rucksack_ERDL"

            ]
        },
        {
            "ClassName": "FOG_Bag_DrawBridge",
            "MaxPriceThreshold": 7500,
            "MinPriceThreshold": 7500,
            "SellPricePercent": 30.0,
            "MaxStockThreshold": 1,
            "MinStockThreshold": 1,
            "QuantityPercent": 0,
            "SpawnAttachments": [],
            "Variants": [
                "FOG_Bag_DrawBridge_CB",
				"FOG_Bag_DrawBridge_RG",
				"FOG_Bag_DrawBridge_OD",
				"FOG_Bag_DrawBridge_Tan",
				"FOG_Bag_DrawBridge_Black",
				"FOG_Bag_DrawBridge_Grey"

            ]
        },
		{
            "ClassName": "FOG_Bag_F4Terminator",
            "MaxPriceThreshold": 9500,
            "MinPriceThreshold": 9500,
            "SellPricePercent": 30.0,
            "MaxStockThreshold": 1,
            "MinStockThreshold": 1,
            "QuantityPercent": 0,
            "SpawnAttachments": [],
            "Variants": [
                "FOG_Bag_F4Terminator",
				"FOG_Bag_F4Terminator_BlackTiger",
				"FOG_Bag_F4Terminator_Black",
				"FOG_Bag_F4Terminator_RG",
				"FOG_Bag_F4Terminator_CB",
				"FOG_Bag_F4Terminator_OD"

            ]
        },
		{
            "ClassName": "FOG_Bag_MRASAP",
            "MaxPriceThreshold": 5500,
            "MinPriceThreshold": 5500,
            "SellPricePercent": 30.0,
            "MaxStockThreshold": 1,
            "MinStockThreshold": 1,
            "QuantityPercent": 0,
            "SpawnAttachments": [],
            "Variants": [
				"FOG_Bag_MRASAP_Black",
				"FOG_Bag_MRASAP_Grey",
				"FOG_Bag_MRASAP_RG",
				"FOG_Bag_MRASAP_CB",
				"FOG_Bag_MRASAP_MC"
            ]
        },
		{
            "ClassName": "FOG_Bag_BlackJack",
            "MaxPriceThreshold": 5500,
            "MinPriceThreshold": 5500,
            "SellPricePercent": 30.0,
            "MaxStockThreshold": 1,
            "MinStockThreshold": 1,
            "QuantityPercent": 0,
            "SpawnAttachments": [],
            "Variants": [
				"FOG_Bag_BlackJack_MC",
				"FOG_Bag_BlackJack_RG",
				"FOG_Bag_BlackJack_CB",
				"FOG_Bag_BlackJack_MCB",
				"FOG_Bag_BlackJack_ERDL",
				"FOG_Bag_BlackJack_Black"

            ]
        },
				{
            "ClassName": "FOG_Bag_SSO",
            "MaxPriceThreshold": 7500,
            "MinPriceThreshold": 7500,
            "SellPricePercent": 30.0,
            "MaxStockThreshold": 1,
            "MinStockThreshold": 1,
            "QuantityPercent": 0,
            "SpawnAttachments": [],
            "Variants": [
				"FOG_Bag_SSO_Tan",
				"FOG_Bag_SSO_Black",
				"FOG_Bag_SSO_MC",
				"FOG_Bag_SSO_CB",
				"FOG_Bag_SSO_MCB",
				"FOG_Bag_SSO_Toxic"

            ]
        },
		{
            "ClassName": "FOG_Bag_Trizip",
            "MaxPriceThreshold": 7500,
            "MinPriceThreshold": 7500,
            "SellPricePercent": 30.0,
            "MaxStockThreshold": 1,
            "MinStockThreshold": 1,
            "QuantityPercent": 0,
            "SpawnAttachments": [],
            "Variants": [
				"FOG_Bag_Trizip_Puke",
				"FOG_Bag_Trizip_Black",
				"FOG_Bag_Trizip_RG",
				"FOG_Bag_Trizip_OD",
				"FOG_Bag_Trizip_CB",
				"FOG_Bag_Trizip_RGCB",
				"FOG_Bag_Trizip_MARPAT",
				"FOG_Bag_Trizip_ATACSFG",
				"FOG_Bag_Trizip_DCU",
				"FOG_Bag_Trizip_ERDL",
				"FOG_Bag_Trizip_MC"
            ]
        }
    ]
}